<?xml version="1.0" encoding="utf-8"?><csslint><file name="assets/dist/css/all-ie8.css"><issue line="85" char="3" severity="warning" reason="Duplicate property 'font-size' found." evidence="  font-size: 19px;"/><issue line="87" char="3" severity="warning" reason="Duplicate property 'line-height' found." evidence="  line-height: 1.3157894737;"/><issue line="134" char="3" severity="warning" reason="Duplicate property 'font-size' found." evidence="  font-size: 48px;"/><issue line="136" char="3" severity="warning" reason="Duplicate property 'line-height' found." evidence="  line-height: 1.0416666667;"/><issue line="151" char="3" severity="warning" reason="Duplicate property 'font-size' found." evidence="  font-size: 36px;"/><issue line="153" char="3" severity="warning" reason="Duplicate property 'line-height' found." evidence="  line-height: 1.1111111111;"/><issue line="168" char="3" severity="warning" reason="Duplicate property 'font-size' found." evidence="  font-size: 24px;"/><issue line="170" char="3" severity="warning" reason="Duplicate property 'line-height' found." evidence="  line-height: 1.25;"/><issue line="185" char="3" severity="warning" reason="Duplicate property 'font-size' found." evidence="  font-size: 19px;"/><issue line="187" char="3" severity="warning" reason="Duplicate property 'line-height' found." evidence="  line-height: 1.3157894737;"/><issue line="201" char="3" severity="warning" reason="Duplicate property 'font-size' found." evidence="  font-size: 27px;"/><issue line="203" char="3" severity="warning" reason="Duplicate property 'line-height' found." evidence="  line-height: 1.1111111111;"/><issue line="216" char="3" severity="warning" reason="Duplicate property 'font-size' found." evidence="  font-size: 24px;"/><issue line="218" char="3" severity="warning" reason="Duplicate property 'line-height' found." evidence="  line-height: 1.25;"/><issue line="222" char="3" severity="warning" reason="Duplicate property 'margin-bottom' found." evidence="  margin-bottom: 0; }"/><issue line="232" char="3" severity="warning" reason="Duplicate property 'font-size' found." evidence="  font-size: 19px;"/><issue line="234" char="3" severity="warning" reason="Duplicate property 'line-height' found." evidence="  line-height: 1.3157894737;"/><issue line="247" char="3" severity="warning" reason="Duplicate property 'font-size' found." evidence="  font-size: 24px;"/><issue line="249" char="3" severity="warning" reason="Duplicate property 'line-height' found." evidence="  line-height: 1.25;"/><issue line="263" char="3" severity="warning" reason="Duplicate property 'font-size' found." evidence="  font-size: 19px;"/><issue line="265" char="3" severity="warning" reason="Duplicate property 'line-height' found." evidence="  line-height: 1.3157894737;"/><issue line="279" char="3" severity="warning" reason="Duplicate property 'font-size' found." evidence="  font-size: 16px;"/><issue line="281" char="3" severity="warning" reason="Duplicate property 'line-height' found." evidence="  line-height: 1.25;"/><issue line="295" char="3" severity="warning" reason="Duplicate property 'font-size' found." evidence="  font-size: 14px;"/><issue line="297" char="3" severity="warning" reason="Duplicate property 'line-height' found." evidence="  line-height: 1.4285714286;"/><issue line="376" char="3" severity="warning" reason="Duplicate property 'width' found." evidence="  width: 25%;"/><issue line="383" char="3" severity="warning" reason="Duplicate property 'width' found." evidence="  width: 33.3333%;"/><issue line="390" char="3" severity="warning" reason="Duplicate property 'width' found." evidence="  width: 50%;"/><issue line="397" char="3" severity="warning" reason="Duplicate property 'width' found." evidence="  width: 66.6666%;"/><issue line="404" char="3" severity="warning" reason="Duplicate property 'width' found." evidence="  width: 75%;"/><issue line="411" char="3" severity="warning" reason="Duplicate property 'width' found." evidence="  width: 100%;"/><issue line="454" char="3" severity="warning" reason="Duplicate property 'padding-top' found." evidence="  padding-top: 40px;"/><issue line="455" char="3" severity="warning" reason="Duplicate property 'padding-bottom' found." evidence="  padding-bottom: 40px; }"/><issue line="466" char="3" severity="warning" reason="Duplicate property 'margin' found." evidence="  margin: 0 auto; }"/><issue line="498" char="3" severity="warning" reason="Duplicate property 'font-size' found." evidence="  font-size: 24px;"/><issue line="500" char="3" severity="warning" reason="Duplicate property 'line-height' found." evidence="  line-height: 1.25;"/><issue line="522" char="3" severity="warning" reason="Duplicate property 'padding-top' found." evidence="  padding-top: 15px;"/><issue line="524" char="3" severity="warning" reason="Duplicate property 'padding-bottom' found." evidence="  padding-bottom: 15px; }"/><issue line="537" char="3" severity="warning" reason="Duplicate property 'font-size' found." evidence="  font-size: 16px;"/><issue line="539" char="3" severity="warning" reason="Duplicate property 'line-height' found." evidence="  line-height: 1.25;"/><issue line="540" char="3" severity="warning" reason="Duplicate property 'font-family' found." evidence="  font-family: 'nta', Arial, sans-serif;"/><issue line="541" char="3" severity="warning" reason="Duplicate property '-webkit-font-smoothing' found." evidence="  -webkit-font-smoothing: antialiased;"/><issue line="542" char="3" severity="warning" reason="Duplicate property '-moz-osx-font-smoothing' found." evidence="  -moz-osx-font-smoothing: grayscale;"/><issue line="642" char="3" severity="warning" reason="Duplicate property 'font-size' found." evidence="  font-size: 16px;"/><issue line="644" char="3" severity="warning" reason="Duplicate property 'line-height' found." evidence="  line-height: 1.25;"/><issue line="690" char="3" severity="warning" reason="Duplicate property 'font-size' found." evidence="  font-size: 16px;"/><issue line="692" char="3" severity="warning" reason="Duplicate property 'line-height' found." evidence="  line-height: 1.25;"/><issue line="712" char="3" severity="warning" reason="float can't be used with display: inline-block." evidence="  float: left; }"/><issue line="729" char="5" severity="warning" reason="Duplicate property 'content' found." evidence="    content: '\003e';"/><issue line="730" char="5" severity="warning" reason="Duplicate property 'width' found." evidence="    width: auto;"/><issue line="731" char="5" severity="warning" reason="Duplicate property 'height' found." evidence="    height: auto;"/><issue line="732" char="5" severity="warning" reason="Duplicate property 'border' found." evidence="    border: 0;"/><issue line="761" char="3" severity="warning" reason="Duplicate property 'font-size' found." evidence="  font-size: 19px;"/><issue line="763" char="3" severity="warning" reason="Duplicate property 'line-height' found." evidence="  line-height: 1;"/><issue line="782" char="3" severity="warning" reason="Duplicate property 'width' found." evidence="  width: auto; }"/><issue line="831" char="1" severity="warning" reason="The properties padding-top, padding-bottom, padding-left, padding-right can be replaced by padding." evidence=".govuk-button--start {"/><issue line="836" char="3" severity="warning" reason="Duplicate property 'font-size' found." evidence="  font-size: 24px;"/><issue line="838" char="3" severity="warning" reason="Duplicate property 'line-height' found." evidence="  line-height: 1;"/><issue line="868" char="3" severity="warning" reason="Duplicate property 'font-size' found." evidence="  font-size: 19px;"/><issue line="870" char="3" severity="warning" reason="Duplicate property 'line-height' found." evidence="  line-height: 1.3157894737;"/><issue line="893" char="3" severity="warning" reason="Duplicate property 'font-size' found." evidence="  font-size: 19px;"/><issue line="895" char="3" severity="warning" reason="Duplicate property 'line-height' found." evidence="  line-height: 1.3157894737;"/><issue line="913" char="3" severity="warning" reason="Duplicate property 'font-size' found." evidence="  font-size: 48px;"/><issue line="915" char="3" severity="warning" reason="Duplicate property 'line-height' found." evidence="  line-height: 1.0416666667;"/><issue line="926" char="3" severity="warning" reason="Duplicate property 'font-size' found." evidence="  font-size: 36px;"/><issue line="928" char="3" severity="warning" reason="Duplicate property 'line-height' found." evidence="  line-height: 1.1111111111;"/><issue line="939" char="3" severity="warning" reason="Duplicate property 'font-size' found." evidence="  font-size: 24px;"/><issue line="941" char="3" severity="warning" reason="Duplicate property 'line-height' found." evidence="  line-height: 1.25;"/><issue line="952" char="3" severity="warning" reason="Duplicate property 'font-size' found." evidence="  font-size: 19px;"/><issue line="954" char="3" severity="warning" reason="Duplicate property 'line-height' found." evidence="  line-height: 1.3157894737; }"/><issue line="969" char="3" severity="warning" reason="Duplicate property 'font-size' found." evidence="  font-size: 19px;"/><issue line="971" char="3" severity="warning" reason="Duplicate property 'line-height' found." evidence="  line-height: 1.3157894737;"/><issue line="994" char="3" severity="warning" reason="Duplicate property 'font-size' found." evidence="  font-size: 19px;"/><issue line="996" char="3" severity="warning" reason="Duplicate property 'line-height' found." evidence="  line-height: 1.3157894737;"/><issue line="1009" char="3" severity="warning" reason="Duplicate property 'font-size' found." evidence="  font-size: 48px;"/><issue line="1011" char="3" severity="warning" reason="Duplicate property 'line-height' found." evidence="  line-height: 1.0416666667;"/><issue line="1022" char="3" severity="warning" reason="Duplicate property 'font-size' found." evidence="  font-size: 36px;"/><issue line="1024" char="3" severity="warning" reason="Duplicate property 'line-height' found." evidence="  line-height: 1.1111111111;"/><issue line="1035" char="3" severity="warning" reason="Duplicate property 'font-size' found." evidence="  font-size: 24px;"/><issue line="1037" char="3" severity="warning" reason="Duplicate property 'line-height' found." evidence="  line-height: 1.25;"/><issue line="1048" char="3" severity="warning" reason="Duplicate property 'font-size' found." evidence="  font-size: 19px;"/><issue line="1050" char="3" severity="warning" reason="Duplicate property 'line-height' found." evidence="  line-height: 1.3157894737; }"/><issue line="1063" char="3" severity="warning" reason="Duplicate property 'font-size' found." evidence="  font-size: 19px;"/><issue line="1065" char="3" severity="warning" reason="Duplicate property 'line-height' found." evidence="  line-height: 1.3157894737;"/><issue line="1169" char="3" severity="warning" reason="Duplicate property 'padding' found." evidence="  padding: 11px 15px 10px 1px; }"/><issue line="1228" char="3" severity="warning" reason="Duplicate property 'font-size' found." evidence="  font-size: 19px;"/><issue line="1230" char="3" severity="warning" reason="Duplicate property 'line-height' found." evidence="  line-height: 1.3157894737;"/><issue line="1245" char="3" severity="warning" reason="margin can't be used with display: table-cell." evidence="  margin: 0;"/><issue line="1313" char="3" severity="warning" reason="Duplicate property 'font-size' found." evidence="  font-size: 19px;"/><issue line="1315" char="3" severity="warning" reason="Duplicate property 'line-height' found." evidence="  line-height: 1.3157894737;"/><issue line="1388" char="3" severity="warning" reason="Duplicate property 'font-size' found." evidence="  font-size: 19px;"/><issue line="1390" char="3" severity="warning" reason="Duplicate property 'line-height' found." evidence="  line-height: 1.3157894737;"/><issue line="1478" char="3" severity="warning" reason="Duplicate property 'font-size' found." evidence="  font-size: 24px;"/><issue line="1480" char="3" severity="warning" reason="Duplicate property 'line-height' found." evidence="  line-height: 1.25;"/><issue line="1493" char="3" severity="warning" reason="Duplicate property 'font-size' found." evidence="  font-size: 19px;"/><issue line="1495" char="3" severity="warning" reason="Duplicate property 'line-height' found." evidence="  line-height: 1.3157894737; }"/><issue line="1524" char="3" severity="warning" reason="Duplicate property 'font-size' found." evidence="  font-size: 19px;"/><issue line="1526" char="3" severity="warning" reason="Duplicate property 'line-height' found." evidence="  line-height: 1.3157894737;"/><issue line="1543" char="3" severity="warning" reason="Duplicate property 'font-size' found." evidence="  font-size: 16px;"/><issue line="1545" char="3" severity="warning" reason="Duplicate property 'line-height' found." evidence="  line-height: 1.25;"/><issue line="1619" char="28" severity="warning" reason="Values of 0 shouldn't have units specified." evidence="  background-position: 50% 0%;"/><issue line="1708" char="3" severity="warning" reason="Duplicate property 'font-size' found." evidence="  font-size: 16px;"/><issue line="1710" char="3" severity="warning" reason="Duplicate property 'line-height' found." evidence="  line-height: 1.25;"/><issue line="1753" char="3" severity="warning" reason="Duplicate property 'font-size' found." evidence="  font-size: 24px;"/><issue line="1755" char="3" severity="warning" reason="Duplicate property 'line-height' found." evidence="  line-height: 1.25;"/><issue line="1796" char="3" severity="warning" reason="Duplicate property 'font-size' found." evidence="  font-size: 24px;"/><issue line="1798" char="3" severity="warning" reason="Duplicate property 'line-height' found." evidence="  line-height: 1.25; }"/><issue line="1806" char="3" severity="warning" reason="Duplicate property 'margin-bottom' found." evidence="  margin-bottom: 10px;"/><issue line="1809" char="3" severity="warning" reason="Duplicate property 'padding-right' found." evidence="  padding-right: 15px;"/><issue line="1826" char="3" severity="warning" reason="Duplicate property 'font-size' found." evidence="  font-size: 16px;"/><issue line="1828" char="3" severity="warning" reason="Duplicate property 'line-height' found." evidence="  line-height: 1.25;"/><issue line="1838" char="3" severity="warning" reason="Duplicate property 'top' found." evidence="  top: 15px; }"/><issue line="1870" char="3" severity="warning" reason="Duplicate property 'margin-bottom' found." evidence="  margin-bottom: 10px;"/><issue line="1900" char="3" severity="warning" reason="Duplicate property 'padding' found." evidence="  padding: 5px 0;"/><issue line="1910" char="5" severity="warning" reason="Duplicate property 'font-size' found." evidence="    font-size: 16px;"/><issue line="1912" char="5" severity="warning" reason="Duplicate property 'line-height' found." evidence="    line-height: 1.25;"/><issue line="1940" char="3" severity="warning" reason="Duplicate property 'font-size' found." evidence="  font-size: 19px;"/><issue line="1942" char="3" severity="warning" reason="Duplicate property 'line-height' found." evidence="  line-height: 1.3157894737;"/><issue line="1965" char="3" severity="warning" reason="Duplicate property 'font-size' found." evidence="  font-size: 19px;"/><issue line="1967" char="3" severity="warning" reason="Duplicate property 'line-height' found." evidence="  line-height: 1.3157894737;"/><issue line="1988" char="3" severity="warning" reason="Duplicate property 'font-size' found." evidence="  font-size: 48px;"/><issue line="1990" char="3" severity="warning" reason="Duplicate property 'line-height' found." evidence="  line-height: 1.0416666667; }"/><issue line="2003" char="3" severity="warning" reason="Duplicate property 'font-size' found." evidence="  font-size: 36px;"/><issue line="2005" char="3" severity="warning" reason="Duplicate property 'line-height' found." evidence="  line-height: 1.1111111111; }"/><issue line="2015" char="3" severity="warning" reason="Duplicate property 'font-size' found." evidence="  font-size: 16px;"/><issue line="2017" char="3" severity="warning" reason="Duplicate property 'line-height' found." evidence="  line-height: 1.25;"/><issue line="2045" char="3" severity="warning" reason="Duplicate property 'font-size' found." evidence="  font-size: 16px;"/><issue line="2047" char="3" severity="warning" reason="Duplicate property 'line-height' found." evidence="  line-height: 1.25;"/><issue line="2067" char="3" severity="warning" reason="Duplicate property 'font-size' found." evidence="  font-size: 19px;"/><issue line="2069" char="3" severity="warning" reason="Duplicate property 'line-height' found." evidence="  line-height: 1.3157894737;"/><issue line="2072" char="3" severity="warning" reason="Duplicate property 'margin-top' found." evidence="  margin-top: 5px;"/><issue line="2084" char="3" severity="warning" reason="Duplicate property 'font-size' found." evidence="  font-size: 19px;"/><issue line="2086" char="3" severity="warning" reason="Duplicate property 'line-height' found." evidence="  line-height: 1.3157894737;"/><issue line="2105" char="3" severity="warning" reason="Duplicate property 'font-family' found." evidence="  font-family: 'nta', Arial, sans-serif;"/><issue line="2106" char="3" severity="warning" reason="Duplicate property '-webkit-font-smoothing' found." evidence="  -webkit-font-smoothing: antialiased;"/><issue line="2107" char="3" severity="warning" reason="Duplicate property '-moz-osx-font-smoothing' found." evidence="  -moz-osx-font-smoothing: grayscale;"/><issue line="2112" char="3" severity="warning" reason="Duplicate property 'font-size' found." evidence="  font-size: 19px;"/><issue line="2114" char="3" severity="warning" reason="Duplicate property 'line-height' found." evidence="  line-height: 1.3157894737;"/><issue line="2164" char="3" severity="warning" reason="The properties padding-top, padding-bottom, padding-left, padding-right can be replaced by padding." evidence="  .js-enabled .govuk-tabs__tab--selected {"/><issue line="2178" char="1" severity="warning" reason="The properties padding-top, padding-bottom, padding-left, padding-right can be replaced by padding." evidence=".js-enabled .govuk-tabs__panel {"/><issue line="2180" char="3" severity="warning" reason="Duplicate property 'margin-bottom' found." evidence="  margin-bottom: 0;"/><issue line="2200" char="3" severity="warning" reason="Duplicate property 'font-size' found." evidence="  font-size: 19px;"/><issue line="2202" char="3" severity="warning" reason="Duplicate property 'line-height' found." evidence="  line-height: 1.3157894737;"/><issue line="2297" char="3" severity="warning" reason="Duplicate property 'font-size' found." evidence="  font-size: 19px;"/><issue line="2299" char="3" severity="warning" reason="Duplicate property 'line-height' found." evidence="  line-height: 1.3157894737;"/><issue line="2333" char="3" severity="warning" reason="Duplicate property 'padding' found." evidence="  padding: 11px 15px 10px 1px; }"/><issue line="2379" char="3" severity="warning" reason="Duplicate property 'font-size' found." evidence="  font-size: 19px;"/><issue line="2381" char="3" severity="warning" reason="Duplicate property 'line-height' found." evidence="  line-height: 1.25;"/><issue line="2416" char="3" severity="warning" reason="Duplicate property 'font-size' found." evidence="  font-size: 16px;"/><issue line="2418" char="3" severity="warning" reason="Duplicate property 'line-height' found." evidence="  line-height: 1.25;"/><issue line="2450" char="3" severity="warning" reason="Duplicate property 'font-size' found." evidence="  font-size: 19px;"/><issue line="2452" char="3" severity="warning" reason="Duplicate property 'line-height' found." evidence="  line-height: 1.3157894737;"/><issue line="2496" char="3" severity="warning" reason="Duplicate property 'font-size' found." evidence="  font-size: 19px;"/><issue line="2498" char="3" severity="warning" reason="Duplicate property 'line-height' found." evidence="  line-height: 1.25;"/><issue line="2525" char="3" severity="warning" reason="Duplicate property 'font-size' found." evidence="  font-size: 19px;"/><issue line="2527" char="3" severity="warning" reason="Duplicate property 'line-height' found." evidence="  line-height: 1.3157894737;"/><issue line="2626" char="3" severity="warning" reason="Duplicate property 'margin' found." evidence="  margin: 0 !important; }"/><issue line="2630" char="3" severity="warning" reason="Duplicate property 'margin-top' found." evidence="  margin-top: 0 !important; }"/><issue line="2634" char="3" severity="warning" reason="Duplicate property 'margin-right' found." evidence="  margin-right: 0 !important; }"/><issue line="2638" char="3" severity="warning" reason="Duplicate property 'margin-bottom' found." evidence="  margin-bottom: 0 !important; }"/><issue line="2642" char="3" severity="warning" reason="Duplicate property 'margin-left' found." evidence="  margin-left: 0 !important; }"/><issue line="2646" char="3" severity="warning" reason="Duplicate property 'margin' found." evidence="  margin: 5px !important; }"/><issue line="2650" char="3" severity="warning" reason="Duplicate property 'margin-top' found." evidence="  margin-top: 5px !important; }"/><issue line="2654" char="3" severity="warning" reason="Duplicate property 'margin-right' found." evidence="  margin-right: 5px !important; }"/><issue line="2658" char="3" severity="warning" reason="Duplicate property 'margin-bottom' found." evidence="  margin-bottom: 5px !important; }"/><issue line="2662" char="3" severity="warning" reason="Duplicate property 'margin-left' found." evidence="  margin-left: 5px !important; }"/><issue line="2666" char="3" severity="warning" reason="Duplicate property 'margin' found." evidence="  margin: 10px !important; }"/><issue line="2670" char="3" severity="warning" reason="Duplicate property 'margin-top' found." evidence="  margin-top: 10px !important; }"/><issue line="2674" char="3" severity="warning" reason="Duplicate property 'margin-right' found." evidence="  margin-right: 10px !important; }"/><issue line="2678" char="3" severity="warning" reason="Duplicate property 'margin-bottom' found." evidence="  margin-bottom: 10px !important; }"/><issue line="2682" char="3" severity="warning" reason="Duplicate property 'margin-left' found." evidence="  margin-left: 10px !important; }"/><issue line="2686" char="3" severity="warning" reason="Duplicate property 'margin' found." evidence="  margin: 15px !important; }"/><issue line="2690" char="3" severity="warning" reason="Duplicate property 'margin-top' found." evidence="  margin-top: 15px !important; }"/><issue line="2694" char="3" severity="warning" reason="Duplicate property 'margin-right' found." evidence="  margin-right: 15px !important; }"/><issue line="2698" char="3" severity="warning" reason="Duplicate property 'margin-bottom' found." evidence="  margin-bottom: 15px !important; }"/><issue line="2702" char="3" severity="warning" reason="Duplicate property 'margin-left' found." evidence="  margin-left: 15px !important; }"/><issue line="2826" char="3" severity="warning" reason="Duplicate property 'padding' found." evidence="  padding: 0 !important; }"/><issue line="2830" char="3" severity="warning" reason="Duplicate property 'padding-top' found." evidence="  padding-top: 0 !important; }"/><issue line="2834" char="3" severity="warning" reason="Duplicate property 'padding-right' found." evidence="  padding-right: 0 !important; }"/><issue line="2838" char="3" severity="warning" reason="Duplicate property 'padding-bottom' found." evidence="  padding-bottom: 0 !important; }"/><issue line="2842" char="3" severity="warning" reason="Duplicate property 'padding-left' found." evidence="  padding-left: 0 !important; }"/><issue line="2846" char="3" severity="warning" reason="Duplicate property 'padding' found." evidence="  padding: 5px !important; }"/><issue line="2850" char="3" severity="warning" reason="Duplicate property 'padding-top' found." evidence="  padding-top: 5px !important; }"/><issue line="2854" char="3" severity="warning" reason="Duplicate property 'padding-right' found." evidence="  padding-right: 5px !important; }"/><issue line="2858" char="3" severity="warning" reason="Duplicate property 'padding-bottom' found." evidence="  padding-bottom: 5px !important; }"/><issue line="2862" char="3" severity="warning" reason="Duplicate property 'padding-left' found." evidence="  padding-left: 5px !important; }"/><issue line="2866" char="3" severity="warning" reason="Duplicate property 'padding' found." evidence="  padding: 10px !important; }"/><issue line="2870" char="3" severity="warning" reason="Duplicate property 'padding-top' found." evidence="  padding-top: 10px !important; }"/><issue line="2874" char="3" severity="warning" reason="Duplicate property 'padding-right' found." evidence="  padding-right: 10px !important; }"/><issue line="2878" char="3" severity="warning" reason="Duplicate property 'padding-bottom' found." evidence="  padding-bottom: 10px !important; }"/><issue line="2882" char="3" severity="warning" reason="Duplicate property 'padding-left' found." evidence="  padding-left: 10px !important; }"/><issue line="2886" char="3" severity="warning" reason="Duplicate property 'padding' found." evidence="  padding: 15px !important; }"/><issue line="2890" char="3" severity="warning" reason="Duplicate property 'padding-top' found." evidence="  padding-top: 15px !important; }"/><issue line="2894" char="3" severity="warning" reason="Duplicate property 'padding-right' found." evidence="  padding-right: 15px !important; }"/><issue line="2898" char="3" severity="warning" reason="Duplicate property 'padding-bottom' found." evidence="  padding-bottom: 15px !important; }"/><issue line="2902" char="3" severity="warning" reason="Duplicate property 'padding-left' found." evidence="  padding-left: 15px !important; }"/><issue line="3028" char="3" severity="warning" reason="Duplicate property 'font-size' found." evidence="  font-size: 80px !important;"/><issue line="3030" char="3" severity="warning" reason="Duplicate property 'line-height' found." evidence="  line-height: 1 !important; }"/><issue line="3036" char="3" severity="warning" reason="Duplicate property 'font-size' found." evidence="  font-size: 48px !important;"/><issue line="3038" char="3" severity="warning" reason="Duplicate property 'line-height' found." evidence="  line-height: 1.0416666667 !important; }"/><issue line="3044" char="3" severity="warning" reason="Duplicate property 'font-size' found." evidence="  font-size: 36px !important;"/><issue line="3046" char="3" severity="warning" reason="Duplicate property 'line-height' found." evidence="  line-height: 1.1111111111 !important; }"/><issue line="3052" char="3" severity="warning" reason="Duplicate property 'font-size' found." evidence="  font-size: 27px !important;"/><issue line="3054" char="3" severity="warning" reason="Duplicate property 'line-height' found." evidence="  line-height: 1.1111111111 !important; }"/><issue line="3060" char="3" severity="warning" reason="Duplicate property 'font-size' found." evidence="  font-size: 24px !important;"/><issue line="3062" char="3" severity="warning" reason="Duplicate property 'line-height' found." evidence="  line-height: 1.25 !important; }"/><issue line="3068" char="3" severity="warning" reason="Duplicate property 'font-size' found." evidence="  font-size: 19px !important;"/><issue line="3070" char="3" severity="warning" reason="Duplicate property 'line-height' found." evidence="  line-height: 1.3157894737 !important; }"/><issue line="3076" char="3" severity="warning" reason="Duplicate property 'font-size' found." evidence="  font-size: 16px !important;"/><issue line="3078" char="3" severity="warning" reason="Duplicate property 'line-height' found." evidence="  line-height: 1.25 !important; }"/><issue line="3084" char="3" severity="warning" reason="Duplicate property 'font-size' found." evidence="  font-size: 14px !important;"/><issue line="3086" char="3" severity="warning" reason="Duplicate property 'line-height' found." evidence="  line-height: 1.4285714286 !important; }"/></file><file name="assets/dist/css/all.css"><issue line="785" char="3" severity="warning" reason="Duplicate property 'font-family' found." evidence="  font-family: 'nta', Arial, sans-serif;"/><issue line="786" char="3" severity="warning" reason="Duplicate property '-webkit-font-smoothing' found." evidence="  -webkit-font-smoothing: antialiased;"/><issue line="787" char="3" severity="warning" reason="Duplicate property '-moz-osx-font-smoothing' found." evidence="  -moz-osx-font-smoothing: grayscale;"/><issue line="999" char="3" severity="warning" reason="float can't be used with display: inline-block." evidence="  float: left; }"/><issue line="1128" char="1" severity="warning" reason="The properties padding-top, padding-bottom, padding-left, padding-right can be replaced by padding." evidence=".govuk-button--start {"/><issue line="2178" char="28" severity="warning" reason="Values of 0 shouldn't have units specified." evidence="  background-position: 50% 0%;"/><issue line="2851" char="3" severity="warning" reason="Duplicate property 'font-family' found." evidence="  font-family: 'nta', Arial, sans-serif;"/><issue line="2852" char="3" severity="warning" reason="Duplicate property '-webkit-font-smoothing' found." evidence="  -webkit-font-smoothing: antialiased;"/><issue line="2853" char="3" severity="warning" reason="Duplicate property '-moz-osx-font-smoothing' found." evidence="  -moz-osx-font-smoothing: grayscale;"/><issue line="2922" char="5" severity="warning" reason="The properties padding-top, padding-bottom, padding-left, padding-right can be replaced by padding." evidence="    .js-enabled .govuk-tabs__tab--selected {"/><issue line="2935" char="3" severity="warning" reason="The properties padding-top, padding-bottom, padding-left, padding-right can be replaced by padding." evidence="  .js-enabled .govuk-tabs__panel {"/></file><file name="assets/dist/css/main.css"><issue line="738" char="3" severity="warning" reason="Duplicate property 'font-family' found." evidence="  font-family: 'nta', Arial, sans-serif;"/><issue line="739" char="3" severity="warning" reason="Duplicate property '-webkit-font-smoothing' found." evidence="  -webkit-font-smoothing: antialiased;"/><issue line="740" char="3" severity="warning" reason="Duplicate property '-moz-osx-font-smoothing' found." evidence="  -moz-osx-font-smoothing: grayscale;"/><issue line="952" char="3" severity="warning" reason="float can't be used with display: inline-block." evidence="  float: left; }"/><issue line="1086" char="1" severity="warning" reason="The properties padding-top, padding-bottom, padding-left, padding-right can be replaced by padding." evidence=".govuk-button--start {"/><issue line="2102" char="28" severity="warning" reason="Values of 0 shouldn't have units specified." evidence="  background-position: 50% 0%;"/><issue line="2754" char="3" severity="warning" reason="Duplicate property 'font-family' found." evidence="  font-family: 'nta', Arial, sans-serif;"/><issue line="2755" char="3" severity="warning" reason="Duplicate property '-webkit-font-smoothing' found." evidence="  -webkit-font-smoothing: antialiased;"/><issue line="2756" char="3" severity="warning" reason="Duplicate property '-moz-osx-font-smoothing' found." evidence="  -moz-osx-font-smoothing: grayscale;"/><issue line="2823" char="5" severity="warning" reason="The properties padding-top, padding-bottom, padding-left, padding-right can be replaced by padding." evidence="    .js-enabled .govuk-tabs__tab--selected {"/><issue line="2836" char="3" severity="warning" reason="The properties padding-top, padding-bottom, padding-left, padding-right can be replaced by padding." evidence="  .js-enabled .govuk-tabs__panel {"/><issue line="4142" char="13" severity="warning" reason="Values of 0 shouldn't have units specified." evidence="    margin: 0px 0px 4px; } }"/><issue line="4142" char="17" severity="warning" reason="Values of 0 shouldn't have units specified." evidence="    margin: 0px 0px 4px; } }"/><issue line="4479" char="15" severity="warning" reason="Values of 0 shouldn't have units specified." evidence="      height: 0px;"/></file></csslint>